pytest_molecule/__init__.py
pytest_molecule/py.typed
pytest_molecule_JC-2.0.0.post2.dist-info/LICENSE
pytest_molecule_JC-2.0.0.post2.dist-info/METADATA
pytest_molecule_JC-2.0.0.post2.dist-info/WHEEL
pytest_molecule_JC-2.0.0.post2.dist-info/entry_points.txt
pytest_molecule_JC-2.0.0.post2.dist-info/top_level.txt
pytest_molecule_JC-2.0.0.post2.dist-info/RECORD
