Metadata-Version: 2.1
Name: pytest-molecule-JC
Version: 2.0.0.post2
Summary: PyTest Molecule Plugin :: discover and run molecule tests
Home-page: https://github.com/LegenJCdary/pytest-molecule
Author: Jakub Wierzbowski
Author-email: jakub.wierzbowski@aptiv.com
Maintainer: Jakub Wierzbowski
Maintainer-email: jakub.wierzbowski@aptiv.com
License: MIT
Keywords: ansible,roles,testing,molecule,pytest,plugin
Platform: UNKNOWN
Classifier: Development Status :: 5 - Production/Stable
Classifier: Environment :: Console
Classifier: Framework :: Pytest
Classifier: Intended Audience :: Developers
Classifier: Intended Audience :: Information Technology
Classifier: Intended Audience :: System Administrators
Classifier: License :: OSI Approved :: MIT License
Classifier: Natural Language :: English
Classifier: Operating System :: OS Independent
Classifier: Programming Language :: Python :: 3
Classifier: Programming Language :: Python :: 3.8
Classifier: Programming Language :: Python :: 3.9
Classifier: Programming Language :: Python :: 3.10
Classifier: Programming Language :: Python :: 3.11
Classifier: Programming Language :: Python :: Implementation :: CPython
Classifier: Programming Language :: Python :: Implementation :: PyPy
Classifier: Topic :: Software Development :: Testing
Classifier: Topic :: System :: Systems Administration
Classifier: Topic :: Utilities
Requires-Python: >=3.8
License-File: LICENSE
Requires-Dist: molecule (>=3.6.0)
Requires-Dist: pytest-html
Requires-Dist: pytest (>=7.0.0)
Provides-Extra: ansi
Requires-Dist: ansi2html ; extra == 'ansi'
Provides-Extra: docker
Requires-Dist: molecule-docker ; extra == 'docker'
Requires-Dist: paramiko (>=2.5.0) ; extra == 'docker'
Provides-Extra: podman
Requires-Dist: molecule-podman ; extra == 'podman'
Provides-Extra: vagrant
Requires-Dist: molecule-vagrant ; extra == 'vagrant'
